MANIFEST.in
README.md
setup.cfg
setup.py
taskserver/__init__.py
taskserver/main.py
taskserver.egg-info/PKG-INFO
taskserver.egg-info/SOURCES.txt
taskserver.egg-info/dependency_links.txt
taskserver.egg-info/top_level.txt
taskserver/app/index.py
taskserver/app/list.py
taskserver/app/run.py
taskserver/app/sidenav.py
taskserver/app/task.py
taskserver/app/config/__init__.py
taskserver/app/config/includes.py
taskserver/app/config/index.py
taskserver/app/config/values.py
taskserver/domain/models/Task.py
taskserver/domain/models/TaskBreakdown.py
taskserver/domain/models/TaskCommand.py
taskserver/domain/models/TaskNode.py
taskserver/domain/models/TaskRun.py
taskserver/domain/models/TaskTimer.py
taskserver/domain/models/TaskTracker.py
taskserver/domain/models/Taskfile.py
taskserver/domain/repositories/__init__.py
taskserver/domain/repositories/base.py
taskserver/domain/repositories/filesystem.py
taskserver/domain/repositories/memory.py
taskserver/domain/serializers/__init__.py
taskserver/domain/serializers/base.py
taskserver/domain/serializers/core.py
taskserver/domain/serializers/run.py
taskserver/domain/serializers/task.py
taskserver/domain/serializers/web.py
taskserver/domain/use_cases/base.py
taskserver/domain/use_cases/config.py
taskserver/domain/use_cases/details.py
taskserver/domain/use_cases/list.py
taskserver/domain/use_cases/run.py
taskserver/domain/use_cases/sidenav.py
taskserver/domain/use_cases/task.py
taskserver/templates/__init__.py
taskserver/templates/base.html
taskserver/templates/index.html
taskserver/templates/icons/arrow-collapse.svg
taskserver/templates/icons/arrow-expand.svg
taskserver/templates/icons/arrow-path.svg
taskserver/templates/icons/arrow-uturn-left.svg
taskserver/templates/icons/back.svg
taskserver/templates/icons/check.svg
taskserver/templates/icons/chevron-down.svg
taskserver/templates/icons/chevron-left.svg
taskserver/templates/icons/chevron-right.svg
taskserver/templates/icons/chevron-up.svg
taskserver/templates/icons/circle-check.svg
taskserver/templates/icons/close.svg
taskserver/templates/icons/cloud-download.svg
taskserver/templates/icons/cloud-upload.svg
