Metadata-Version: 2.1
Name: taskserver
Version: 0.0.5
Summary: Simple task server built on top of Taskfile
Home-page: https://github.com/planet-lodder/taskserver.py
Download-URL: https://github.com/planet-lodder/taskserver.py/archive/refs/tags/0.0.5.tar.gz
Author: Club404
Author-email: info@club404.io
License: MIT
Keywords: taskfile,http,server
Classifier: Development Status :: 3 - Alpha
Classifier: Intended Audience :: Developers
Classifier: Topic :: Software Development :: Build Tools
Classifier: License :: OSI Approved :: MIT License
Classifier: Programming Language :: Python :: 3
Classifier: Programming Language :: Python :: 3.4
Classifier: Programming Language :: Python :: 3.5
Classifier: Programming Language :: Python :: 3.6
